etc_jupyterlab_nbgrader_validate/__init__.py
etc_jupyterlab_nbgrader_validate/_version.py
etc_jupyterlab_nbgrader_validate/handlers.py
etc_jupyterlab_nbgrader_validate-4.0.0.data/data/etc/jupyter/jupyter_server_config.d/etc_jupyterlab_nbgrader_validate.json
etc_jupyterlab_nbgrader_validate-4.0.0.data/data/share/jupyter/labextensions/@educational-technology-collective/etc_jupyterlab_nbgrader_validate/package.json
etc_jupyterlab_nbgrader_validate-4.0.0.data/data/share/jupyter/labextensions/@educational-technology-collective/etc_jupyterlab_nbgrader_validate/schemas/@educational-technology-collective/etc_jupyterlab_nbgrader_validate/package.json.orig
etc_jupyterlab_nbgrader_validate-4.0.0.data/data/share/jupyter/labextensions/@educational-technology-collective/etc_jupyterlab_nbgrader_validate/schemas/@educational-technology-collective/etc_jupyterlab_nbgrader_validate/plugin.json
etc_jupyterlab_nbgrader_validate-4.0.0.data/data/share/jupyter/labextensions/@educational-technology-collective/etc_jupyterlab_nbgrader_validate/static/747.981b3a7f5d037712d9b7.js
etc_jupyterlab_nbgrader_validate-4.0.0.data/data/share/jupyter/labextensions/@educational-technology-collective/etc_jupyterlab_nbgrader_validate/static/763.f7218ffc84afd8641a4f.js
etc_jupyterlab_nbgrader_validate-4.0.0.data/data/share/jupyter/labextensions/@educational-technology-collective/etc_jupyterlab_nbgrader_validate/static/remoteEntry.15f6006fadb3be3daad7.js
etc_jupyterlab_nbgrader_validate-4.0.0.data/data/share/jupyter/labextensions/@educational-technology-collective/etc_jupyterlab_nbgrader_validate/static/style.js
etc_jupyterlab_nbgrader_validate-4.0.0.data/data/share/jupyter/labextensions/@educational-technology-collective/etc_jupyterlab_nbgrader_validate/static/third-party-licenses.json
etc_jupyterlab_nbgrader_validate-4.0.0.data/data/share/jupyter/labextensions/@educational-technology-collective/etc_jupyterlab_nbgrader_validate/install.json
etc_jupyterlab_nbgrader_validate-4.0.0.dist-info/METADATA
etc_jupyterlab_nbgrader_validate-4.0.0.dist-info/WHEEL
etc_jupyterlab_nbgrader_validate-4.0.0.dist-info/licenses/LICENSE
etc_jupyterlab_nbgrader_validate-4.0.0.dist-info/RECORD
