Metadata-Version: 2.3
Name: etc_jupyterlab_nbgrader_validate
Version: 4.0.0
Dynamic: Keywords
Summary: A JupyterLab extension.
Project-URL: Homepage, https://github.com/educational-technology-collective/etc_jupyterlab_nbgrader_validate
Project-URL: Bug Tracker, https://github.com/educational-technology-collective/etc_jupyterlab_nbgrader_validate/issues
Project-URL: Repository, https://github.com/educational-technology-collective/etc_jupyterlab_nbgrader_validate.git
Author: ETC
License: BSD 3-Clause License
License-File: LICENSE
Classifier: Framework :: Jupyter
Classifier: Framework :: Jupyter :: JupyterLab
Classifier: Framework :: Jupyter :: JupyterLab :: 4
Classifier: Framework :: Jupyter :: JupyterLab :: Extensions
Classifier: Framework :: Jupyter :: JupyterLab :: Extensions :: Prebuilt
Classifier: License :: OSI Approved :: BSD License
Classifier: Programming Language :: Python
Classifier: Programming Language :: Python :: 3
Classifier: Programming Language :: Python :: 3.8
Classifier: Programming Language :: Python :: 3.9
Classifier: Programming Language :: Python :: 3.10
Classifier: Programming Language :: Python :: 3.11
Classifier: Programming Language :: Python :: 3.12
Requires-Python: >=3.8
Requires-Dist: jupyter-server<3,>=2.0.1
Requires-Dist: jupyterlab-pioneer>=1.2.0
Requires-Dist: nbgrader
